{
  "swagger": "2.0",
  "info": {
    "title": "ocp-note-api.proto",
    "version": "version not set"
  },
  "consumes": [
    "application/json"
  ],
  "produces": [
    "application/json"
  ],
  "paths": {
    "/v1/note": {
      "post": {
        "operationId": "OcpNoteApi_CreateNoteV1",
        "responses": {
          "200": {
            "description": "A successful response.",
            "schema": {
              "$ref": "#/definitions/apiCreateNoteV1Response"
            }
          },
          "default": {
            "description": "An unexpected error response.",
            "schema": {
              "$ref": "#/definitions/runtimeError"
            }
          }
        },
        "tags": [
          "OcpNoteApi"
        ]
      }
    },
    "/v1/notes": {
      "get": {
        "operationId": "OcpNoteApi_ListNotesV1",
        "responses": {
          "200": {
            "description": "A successful response.",
            "schema": {
              "$ref": "#/definitions/apiListNotesV1Response"
            }
          },
          "default": {
            "description": "An unexpected error response.",
            "schema": {
              "$ref": "#/definitions/runtimeError"
            }
          }
        },
        "parameters": [
          {
            "name": "limit",
            "in": "query",
            "required": false,
            "type": "string",
            "format": "int64"
          },
          {
            "name": "offset",
            "in": "query",
            "required": false,
            "type": "string",
            "format": "int64"
          }
        ],
        "tags": [
          "OcpNoteApi"
        ]
      },
      "post": {
        "operationId": "OcpNoteApi_MultiCreateNotesV1",
        "responses": {
          "200": {
            "description": "A successful response.",
            "schema": {
              "$ref": "#/definitions/apiMultiCreateNotesV1Response"
            }
          },
          "default": {
            "description": "An unexpected error response.",
            "schema": {
              "$ref": "#/definitions/runtimeError"
            }
          }
        },
        "tags": [
          "OcpNoteApi"
        ]
      }
    },
    "/v1/notes/{note_id}": {
      "get": {
        "operationId": "OcpNoteApi_DescribeNoteV1",
        "responses": {
          "200": {
            "description": "A successful response.",
            "schema": {
              "$ref": "#/definitions/apiDescribeNoteV1Response"
            }
          },
          "default": {
            "description": "An unexpected error response.",
            "schema": {
              "$ref": "#/definitions/runtimeError"
            }
          }
        },
        "parameters": [
          {
            "name": "note_id",
            "in": "path",
            "required": true,
            "type": "string",
            "format": "int64"
          }
        ],
        "tags": [
          "OcpNoteApi"
        ]
      },
      "delete": {
        "operationId": "OcpNoteApi_RemoveNoteV1",
        "responses": {
          "200": {
            "description": "A successful response.",
            "schema": {
              "$ref": "#/definitions/apiRemoveNoteV1Response"
            }
          },
          "default": {
            "description": "An unexpected error response.",
            "schema": {
              "$ref": "#/definitions/runtimeError"
            }
          }
        },
        "parameters": [
          {
            "name": "note_id",
            "in": "path",
            "required": true,
            "type": "string",
            "format": "int64"
          }
        ],
        "tags": [
          "OcpNoteApi"
        ]
      }
    }
  },
  "definitions": {
    "apiCreateNoteV1Response": {
      "type": "object",
      "properties": {
        "note_id": {
          "type": "string",
          "format": "uint64"
        }
      }
    },
    "apiDescribeNoteV1Response": {
      "type": "object",
      "properties": {
        "note": {
          "$ref": "#/definitions/apiNote"
        }
      }
    },
    "apiListNotesV1Response": {
      "type": "object",
      "properties": {
        "notes": {
          "type": "array",
          "items": {
            "$ref": "#/definitions/apiNote"
          }
        }
      }
    },
    "apiMultiCreateNotesV1Response": {
      "type": "object",
      "properties": {
        "number_of_notes_created": {
          "type": "string",
          "format": "uint64"
        }
      }
    },
    "apiNewNote": {
      "type": "object",
      "properties": {
        "user_id": {
          "type": "integer",
          "format": "int32"
        },
        "classroom_id": {
          "type": "integer",
          "format": "int32"
        },
        "document_id": {
          "type": "integer",
          "format": "int32"
        }
      }
    },
    "apiNote": {
      "type": "object",
      "properties": {
        "id": {
          "type": "string",
          "format": "uint64"
        },
        "user_id": {
          "type": "integer",
          "format": "int64"
        },
        "classroom_id": {
          "type": "integer",
          "format": "int64"
        },
        "document_id": {
          "type": "integer",
          "format": "int64"
        }
      }
    },
    "apiRemoveNoteV1Response": {
      "type": "object",
      "properties": {
        "found": {
          "type": "boolean"
        }
      }
    },
    "protobufAny": {
      "type": "object",
      "properties": {
        "type_url": {
          "type": "string"
        },
        "value": {
          "type": "string",
          "format": "byte"
        }
      }
    },
    "runtimeError": {
      "type": "object",
      "properties": {
        "error": {
          "type": "string"
        },
        "code": {
          "type": "integer",
          "format": "int32"
        },
        "message": {
          "type": "string"
        },
        "details": {
          "type": "array",
          "items": {
            "$ref": "#/definitions/protobufAny"
          }
        }
      }
    }
  }
}
